{
  "basics": {
    "name": "Caleb Simmons",
    "label": "Full Stack Web Application Engineer",
    "email": "caleb.t.simmons@gmail.com",
    "phone": "(443) 907-5931",
    "website": "https://www.linkedin.com/in/calebsimmons/",
    "summary": " Caleb is a web application engineer living in Baltimore County, Maryland. Throughout his career, Caleb has worked on projects that have improved his employers' customer relationships, business analytics, and overall productivity. Caleb studied Mathematics and Statistics at the University of Maryland, Baltimore County. During his studies, Caleb became knowledgeable of sophisticated Machine Learning techniques that he implements in his applications for automated decision making. Caleb dedicates himself to being a polyglot programmer and life long learner, so that he can use the best possible tools to solve the problem at hand.",
    "location": {
      "address": "8005 Ridgetown Drive",
      "postalCode": "21236",
      "city": "Nottingham",
      "countryCode": "US",
      "region": "Maryland"
    },
    "profiles": []
  },
  "work": [
    {
      "company": "Sogeti USA, LLC.",
      "position": "Consultant",
      "website": "https://us.sogeti.com",
      "startDate": "05/01/2017",
      "endDate": "Present",
      "highlights": [
        "Expert on front end architecture, cloud infrastructure, and hybrid mobile technologies",
        "Became a trusted advisor to clients by always delivering above expectations and making recommendations based on the best interests of the client",
        "Provided advice to consultants nationwide to help Sogeti win bids and maintain delivery excellence"
      ],
      "clients": [
        {
          "company": "Amtrak",
          "website": "https://amtrak.com",
          "startDate": "07/28/2017",
          "endDate": "Present",
          "highlights": [
            "Delivered UI enhancements for tickets.amtrak.com using mastery of several front end technologies",
            "Developed a completely new solution for train seat selection during trip booking, a feature that did not exist beforehand",
            "Made recommendations for the front end architecture for future Amtrak web projects",
            "Supervised enhancements of Amtrak's mobile application built using the Ionic framework",
            "Identified vue.js as a powerful tool to build web components in Adobe Experience Manager, and started utilizing it across Amtrak's CMS",
            "Proactively sought out outstanding defects in production Java server code and fixed them"
          ]
        }
      ]
    },
    {
      "company": "Freedmont Mortgage Funding",
      "position": "Web and Mobile Application Engineer",
      "website": "https://freedmont.com",
      "startDate": "06/15/2015",
      "endDate": "05/01/2017",
      "highlights": [
		    "Gained industry experience by earning a mortgage loan origination license",  
        "Built a proprietary mobile CRM using the Ionic framework",
        "Used Flask and Twillio to develop a mortgage lead distribution system via SMS",
		    "Hosted Applications on Microsoft Azure and Amazon Web Services",  
		    "Built applications to update in real time with the Reactivex library",  
        "Used existing software's APIs to build custom chrome extensions that integrated with legacy systems"
      ]
    },
    {
      "company": "Quantum Lean, LLC.",
      "position": "ERP Specialist",
      "website": "",
      "startDate": "07/28/2014",
      "endDate": "06/14/2015",
      "highlights": [
        "Used a genetic algorithm to optimize scheduling efficiency",
        "Generated custom production reports with SQL",
        "Trained employees on Lean Manufacturing and ERP best practices"
      ]
    },
    {
      "company": "University of Maryland, Baltimore County",
      "position": "Erill Lab - Research Assistant",
      "website": "http://erilllab.umbc.edu/",
      "startDate": "08/20/2012",
      "endDate": "05/21/2014",
      "highlights": [
        "Helped maintain the CollectTF web application built with Django",
        "Used Python to construct and optimize computational biology models",
        "Presented research at multi-institution hosted conferences"
      ]
    }
  ],
  "education": [
    {
      "institution": "University of Maryland, Baltimore County",
      "area": "Information Systems",
      "studyType": "Master of Science",
      "startDate": "01/29/2018",
      "endDate": "Expected 2020"
    },
    {
      "institution": "University of Maryland, Baltimore County",
      "area": "Mathematics",
      "studyType": "Bachelor of Science",
      "startDate": "08/21/2010",
      "endDate": "05/21/2014"
    }
  ],
  "skills": [
    {
      "name": "Languages",
      "level": "",
      "keywords": [
        "Javascript",
        "HTML",
        "CSS",
        "Typescript",
        "Python",
        "C#",
        "Java",
        "SQL",
        "R & SAS",
		    "UNIX command line",
		    "Windows Powershell"  
      ]
    },
    {
      "name": "Front-End",
      "level": "",
      "keywords": [
        "Angular.js (v1) & Angular (v2+)",
        "React",
        "Vue.js",
		    "React Native",  
        "Ionic Mobile Framework",
        "Phonegap",
		    "Cordova",		  
		    "Xamarin",
        "jQuery",
        "prototype.js",
        "sightly",
        "Sass",
        "Bootstrap"
      ]
    },
    {
      "name": "Back-End",
      "level": "",
      "keywords": [
        "REST APIs",
		    "Django",  
        "Flask",
        "node.js",
        ".NET",
        "Java Server Pages (.jsp)",
        "SQL/Relational Databases",
        "NoSQL Databases",
        "Firebase",
		    "Reactivex",
		    "Microsoft Azure",
		    "Amazon Web Services",
        "npm",
        "Adobe Experience Manager"
      ]
    }
  ]
}